README.md
setup.py
pyrcon4squad/__init__.py
pyrcon4squad/exceptions.py
pyrcon4squad/rcon.py
pyrcon4squad/rcon_packet.py
pyrcon4squad.egg-info/PKG-INFO
pyrcon4squad.egg-info/SOURCES.txt
pyrcon4squad.egg-info/dependency_links.txt
pyrcon4squad.egg-info/top_level.txt