Metadata-Version: 2.2
Name: pyrcon4squad
Version: 0.1.1
Summary: A simple python rcon package for squad
Author: guyuemochen
License: MIT
Dynamic: author
Dynamic: description
Dynamic: description-content-type
Dynamic: license
Dynamic: summary
